gain_requests_futures/__init__.py
gain_requests_futures/sessions.py
gain_requests_futures-0.9.7.dist-info/DESCRIPTION.rst
gain_requests_futures-0.9.7.dist-info/METADATA
gain_requests_futures-0.9.7.dist-info/RECORD
gain_requests_futures-0.9.7.dist-info/WHEEL
gain_requests_futures-0.9.7.dist-info/metadata.json
gain_requests_futures-0.9.7.dist-info/top_level.txt
