Metadata-Version: 2.0
Name: gain-requests-futures
Version: 0.9.7
Summary: Asynchronous Python HTTP for Humans.
Home-page: https://github.com/GainCompliance/gain-requests-futures
Author: Ross McFarland
Author-email: rwmcfa1@neces.com
License: Apache License v2
Platform: UNKNOWN
Classifier: Development Status :: 5 - Production/Stable
Classifier: Intended Audience :: Developers
Classifier: Natural Language :: English
Classifier: License :: OSI Approved :: Apache Software License
Classifier: Programming Language :: Python
Classifier: Programming Language :: Python :: 2.7
Classifier: Programming Language :: Python :: 3
Classifier: Programming Language :: Python :: 3.3
Classifier: Programming Language :: Python :: 3.4
Classifier: Programming Language :: Python :: 3.5
Requires-Dist: requests (>=1.2.0)
Requires-Dist: futures (>=2.1.3)
